{
    "$id": "methods-directory/legacy/localorbital",
    "$schema": "http://json-schema.org/draft-07/schema#",
    "title": "legacy method localorbital",
    "type": "object",
    "required": [
        "type",
        "subtype"
    ],
    "properties": {
        "type": {
            "enum": [
                "localorbital"
            ],
            "description": "general type of this method, eg. `pseudopotential`",
            "type": "string"
        },
        "subtype": {
            "enum": [
                "pople"
            ],
            "description": "general subtype of this method, eg. `ultra-soft`",
            "type": "string"
        },
        "precision": {
            "description": "Object showing the actual possible precision based on theory and implementation",
            "type": "object"
        },
        "data": {
            "description": "additional data specific to method, eg. array of pseudopotentials",
            "type": "object"
        }
    }
}