{
    "schemaId": "method_units/mathematical/intgr/diffeq/order1",
    "$schema": "http://json-schema.org/draft-04/schema#",
    "description": "Methods for the numerical integration of differential equations",
    "allOf": [
        {
            "$ref": "../diffeq.json"
        }
    ],
    "properties": {
        "categories": {
            "properties": {
                "tier3": {
                    "enum": [
                        {
                            "name": "First Order Integrator",
                            "slug": "order1"
                        }
                    ]
                }
            }
        }
    }
}
