{
    "$id": "properties-directory/structural/lattice/lattice-vectors",
    "$schema": "http://json-schema.org/draft-07/schema#",
    "title": "lattice explicit unit",
    "type": "object",
    "allOf": [
        {
            "$ref": "../../../core/abstract/3d_vector_basis.json"
        }
    ],
    "properties": {
        "alat": {
            "description": "lattice parameter for fractional coordinates",
            "type": "number",
            "default": 1
        },
        "units": {
            "$ref": "../../../definitions/units.json#/length"
        }
    }
}
