{
    "$schema": "http://json-schema.org/draft-04/schema#",
    "title": "data IO unit schema",
    "type": "object",
    "allOf": [
        {
            "$ref": "../unit.json"
        }
    ],
    "properties": {
        "type": {
            "enum": [
                "io"
            ]
        },
        "io": {
            "type": "object",
            "properties": {
                "subtype": {
                    "enum": [
                        "input"
                    ]
                },
                "flavor": {
                    "enum": [
                        "api"
                    ]
                },
                "input": {
                    "type": "array",
                    "items": {
                        "anyOf": [
                            {
                                "$ref": "file:data_io/rest_api.json"
                            }
                        ]
                    }
                }
            },
            "required": [
                "subtype",
                "flavor",
                "input"
            ]
        }
    }
}
