{
    "$schema": "http://json-schema.org/draft-04/schema#",
    "title": "ionic convergence schema",
    "allOf": [
        {
            "$ref": "file:../../../../job/workflow/unit/convergence.json"
        }
    ],
    "properties": {
        "name": {
            "enum": [
                "ionic"
            ]
        },
        "tolerance": {
            "description": "for ionic convergence tolerance shows force tolerance"
        },
        "units": {
            "description": "units for force tolerance",
            "enum": [
                "eV/a.u."
            ]
        },
        "data": {
            "description": "energetic and structural information",
            "items": {
                "type": "object",
                "properties": {
                    "energy": {
                        "description": "converged electronic energy for this structure (last in `electronic`)",
                        "type": "number"
                    },
                    "structure": {
                        "description": "TODO: structural information at each step to be here",
                        "type": "object"
                    },
                    "electronic": {
                        "description": "data about electronic at this ionic step",
                        "$ref": "file:electronic.json"
                    }
                }
            }
        }
    },
    "required": [
        "data"
    ]
}
