{
    "name": "potential_profile",
    "xAxis": {
        "label": "z coordinate"
    },
    "xDataArray": [
        -4.89,
        -4.78,
        -4.67,
        -4.56,
        -4.44,
        -4.33,
        -4.22,
        -4.11,
        -4.0,
        -3.89,
        -3.78,
        -3.67,
        -3.56,
        -3.44,
        -3.33,
        -3.22,
        -3.11,
        -3.0,
        -2.89,
        -2.78,
        -2.67,
        -2.56,
        -2.44,
        -2.33,
        -2.22,
        -2.11,
        -2.0,
        -1.89,
        -1.78,
        -1.67,
        -1.56,
        -1.44,
        -1.33,
        -1.22,
        -1.11,
        -1.0,
        -0.89,
        -0.78,
        -0.67,
        -0.56,
        -0.44,
        -0.33,
        -0.22,
        -0.11,
        0.0,
        0.11,
        0.22,
        0.33,
        0.44,
        0.56,
        0.67,
        0.78,
        0.89,
        1.0,
        1.11,
        1.22,
        1.33,
        1.44,
        1.56,
        1.67,
        1.78,
        1.89,
        2.0,
        2.11,
        2.22,
        2.33,
        2.44,
        2.56,
        2.67,
        2.78,
        2.89,
        3.0,
        3.11,
        3.22,
        3.33,
        3.44,
        3.56,
        3.67,
        3.78,
        3.89,
        4.0,
        4.11,
        4.22,
        4.33,
        4.44,
        4.56,
        4.67,
        4.78,
        4.89,
        5.0
    ],
    "yAxis": {
        "label": "energy",
        "units": "eV"
    },
    "yDataSeries": [
        [
            -6.5847438,
            -7.0900648,
            -7.5601238,
            -7.9743444,
            -8.317498,
            -8.5750414,
            -8.7323531,
            -8.7756094,
            -8.6928512,
            -8.4749404,
            -8.1163004,
            -7.6153986,
            -6.9750523,
            -6.2024685,
            -5.3089481,
            -4.3094252,
            -3.221664,
            -2.0651055,
            -0.8595908,
            0.3757683,
            1.621476,
            2.8529103,
            4.0369176,
            5.1373585,
            6.128644,
            7.0045825,
            7.7712809,
            8.4304426,
            8.9723819,
            9.3871685,
            9.6802603,
            9.8747178,
            9.9992373,
            10.0759107,
            10.1179921,
            10.1347721,
            10.135308,
            10.1284733,
            10.1216396,
            10.1194728,
            10.123169,
            10.1302705,
            10.135054,
            10.1294748,
            10.1044686,
            10.0510636,
            9.9592008,
            9.8128981,
            9.5869054,
            9.2527843,
            8.792791,
            8.2080433,
            7.5104019,
            6.7059964,
            5.7898881,
            4.7584964,
            3.6248929,
            2.4199496,
            1.1800743,
            -0.0644968,
            -1.2915708,
            -2.4821713,
            -3.6168812,
            -4.6758484,
            -5.6400841,
            -6.4926969,
            -7.2199594,
            -7.8119595,
            -8.2630068,
            -8.5718294,
            -8.7414172,
            -8.7786597,
            -8.6937792,
            -8.4995045,
            -8.2100616,
            -7.8401116,
            -7.4041858,
            -6.9186421,
            -6.4075296,
            -5.9071307,
            -5.4606271,
            -5.1040446,
            -4.8555018,
            -4.7166747,
            -4.6829599,
            -4.7525548,
            -4.9289007,
            -5.2156826,
            -5.6063933,
            -6.0761488
        ],
        [
            6.4872255,
            8.2828137,
            10.1322914,
            11.9417738,
            13.6185904,
            15.0903496,
            16.2665057,
            17.0759068,
            17.5243394,
            17.6353196,
            17.4067567,
            16.8407456,
            15.936368,
            14.6933999,
            13.1092068,
            11.1556308,
            8.8495816,
            6.2782925,
            3.5236735,
            0.6615537,
            -2.231828,
            -5.0789168,
            -7.7515245,
            -10.1125293,
            -12.0638856,
            -13.5188149,
            -14.4270666,
            -14.7810887,
            -14.5951143,
            -13.9316117,
            -12.8794348,
            -11.5441718,
            -10.0684005,
            -8.5678288,
            -7.1150814,
            -5.7882775,
            -4.662425,
            -3.8235347,
            -3.3501462,
            -3.2391711,
            -3.4727226,
            -4.078392,
            -5.0288731,
            -6.2333349,
            -7.6130396,
            -9.0904141,
            -10.5910618,
            -12.0334084,
            -13.2838966,
            -14.2097789,
            -14.7154687,
            -14.7162866,
            -14.1681033,
            -13.0660817,
            -11.4286451,
            -9.3237245,
            -6.8409853,
            -4.0902654,
            -1.2157129,
            1.6742574,
            4.5079019,
            7.2063751,
            9.6955033,
            11.8859592,
            13.7077246,
            15.1701504,
            16.2953188,
            17.080648,
            17.5290535,
            17.6384205,
            17.4099184,
            16.8389864,
            15.898065,
            14.6073537,
            13.0547946,
            11.3229031,
            9.4872236,
            7.6477713,
            5.8832037,
            4.2217008,
            2.7122165,
            1.4586801,
            0.5385618,
            -0.0162883,
            -0.1590433,
            0.1332448,
            0.8194274,
            1.860338,
            3.2151603,
            4.7874983
        ],
        [
            -0.0975183,
            1.192749,
            2.5721676,
            3.9674294,
            5.3010924,
            6.5153082,
            7.5341527,
            8.3002974,
            8.8314882,
            9.1603792,
            9.2904563,
            9.225347,
            8.9613157,
            8.4909315,
            7.8002586,
            6.8462056,
            5.6279176,
            4.213187,
            2.6640827,
            1.0373219,
            -0.610352,
            -2.2260065,
            -3.7146069,
            -4.9751708,
            -5.9352416,
            -6.5142324,
            -6.6557857,
            -6.3506462,
            -5.6227323,
            -4.5444432,
            -3.1991744,
            -1.669454,
            -0.0691632,
            1.5080819,
            3.0029107,
            4.3464946,
            5.472883,
            6.3049385,
            6.7714934,
            6.8803016,
            6.6504464,
            6.0518785,
            5.1061809,
            3.8961399,
            2.491429,
            0.9606496,
            -0.631861,
            -2.2205103,
            -3.6969912,
            -4.9569946,
            -5.9226777,
            -6.5082433,
            -6.6577015,
            -6.3600852,
            -5.638757,
            -4.5652281,
            -3.2160924,
            -1.6703158,
            -0.0356385,
            1.6097606,
            3.2163311,
            4.7242038,
            6.0786221,
            7.2101108,
            8.0676405,
            8.6774535,
            9.0753594,
            9.2686885,
            9.2660468,
            9.0665911,
            8.6685013,
            8.0603268,
            7.2042858,
            6.1078493,
            4.844733,
            3.4827915,
            2.0830378,
            0.7291291,
            -0.5243259,
            -1.6854299,
            -2.7484106,
            -3.6453644,
            -4.3169401,
            -4.732963,
            -4.8420032,
            -4.61931,
            -4.1094733,
            -3.3553446,
            -2.391233,
            -1.2886506
        ]
    ]
}
