{
    "$schema": "http://json-schema.org/draft-04/schema#",
    "title": "ML model data schema",
    "properties": {
        "algorithm": {
            "type": "string",
            "description": "name of the ML algorithm. Example: linear_regression"
        },
        "task": {
            "type": "string",
            "description": "description of ML task. Example: property prediction"
        },
        "property": {
            "type": "string",
            "description": "name of the predicted or optimized characteristic"
        },
        "modelParameters": {
            "type": "object",
            "description": "parameters of the fitted model. Example: regression model coefficients, score, intercept and data",
            "properties": {
                "modelCoefficients": {
                    "type": "array",
                    "description": "weights/coefficients of the function from linear or non-linear fit"
                },
                "intercept": {
                    "type": "number",
                    "description": "intercept from the linear fit of data points"
                },
                "score":{
                    "type": "number",
                    "description": "metric for accuracy of the model"
                },
                "modelData": {
                    "type": "object",
                    "description": "JSON object of input data used for model fitting"
                }
            }
        }
    },
    "required": [
        "algorithm",
        "task",
        "property",
        "modelParameters"
    ]
}
